cen/__init__.py
cen/cli.py
cen/repo.py
cen_dev-0.1.11.dist-info/entry_points.txt
cen_dev-0.1.11.dist-info/WHEEL
cen_dev-0.1.11.dist-info/METADATA
cen_dev-0.1.11.dist-info/RECORD
