Metadata-Version: 2.1
Name: cen-dev
Version: 0.1.11
Summary: Centra developer commanl line tool
Home-page: https://centra.ai
License: MIT
Keywords: centra,dev
Author: Centra Dev Team
Author-email: hello@centra.ai
Requires-Python: >=3.7,<4.0
Classifier: License :: OSI Approved :: MIT License
Classifier: Programming Language :: Python :: 3
Classifier: Programming Language :: Python :: 3.7
Classifier: Programming Language :: Python :: 3.8
Classifier: Programming Language :: Python :: 3.9
Classifier: Programming Language :: Python :: 3.10
Classifier: Programming Language :: Python :: 3.11
Requires-Dist: cookiecutter (>=2.1.1,<3.0.0)
Requires-Dist: fire (>=0.5.0,<0.6.0)
Project-URL: Repository, https://centra.ai/dev/
